<?xml version='1.0' encoding='UTF-8'?>
<types:mule xmlns:types="http://www.mulesoft.org/schema/mule/types">
  <types:catalog>
    <types:type name="auto_c6d7d691-eb14-4d53-bb75-54856400c996_Output-Attributes" format="java">
      <types:shape format="weave" example="weave/autogenerated/c6d7d691-eb14-4d53-bb75-54856400c996/Output-Attributes.wev" autogeneratedOrigin="ff7681b9-79f3-4584-87cd-5db80fe6230e"><![CDATA[%dw 2.0

type auto_c6d7d691_eb14_4d53_bb75_54856400c996_Output_Attributes = {|
  listenerPath: String, 
  rawRequestPath: String, 
  relativePath: String, 
  maskedRequestPath: String, 
  version: String, 
  scheme: String, 
  method: String, 
  requestUri: String, 
  rawRequestUri: String, 
  queryString: String, 
  localAddress: String, 
  remoteAddress: String, 
  clientCertificate?: java_security_cert_Certificate, 
  queryParams: { _?: String }, 
  uriParams: { _?: String }, 
  requestPath: String, 
  headers: { _?: String }
|} {"typeAlias": "HttpRequestAttributes",
"typeId": "org.mule.extension.http.api.HttpRequestAttributes"}
type java_security_cert_Certificate = {|
  encoded?: Binary, 
  publicKey?: java_security_PublicKey, 
  "type"?: String
|} {"typeAlias": "Certificate",
"typeId": "java.security.cert.Certificate"}
type java_security_PublicKey = {|  |} {"typeAlias": "PublicKey",
"typeId": "java.security.PublicKey"}





]]></types:shape>
    </types:type>
    <types:type name="auto_c6d7d691-eb14-4d53-bb75-54856400c996_Input-Attributes" format="java">
      <types:shape format="weave" example="weave/autogenerated/c6d7d691-eb14-4d53-bb75-54856400c996/Input-Attributes.wev" autogeneratedOrigin="ff7681b9-79f3-4584-87cd-5db80fe6230e"><![CDATA[%dw 2.0

type auto_c6d7d691_eb14_4d53_bb75_54856400c996_Input_Attributes = {|
  listenerPath: String, 
  rawRequestPath: String, 
  relativePath: String, 
  maskedRequestPath: String, 
  version: String, 
  scheme: String, 
  method: String, 
  requestUri: String, 
  rawRequestUri: String, 
  queryString: String, 
  localAddress: String, 
  remoteAddress: String, 
  clientCertificate?: java_security_cert_Certificate, 
  queryParams: { _?: String }, 
  uriParams: { _?: String }, 
  requestPath: String, 
  headers: { _?: String }
|} {"typeAlias": "HttpRequestAttributes",
"typeId": "org.mule.extension.http.api.HttpRequestAttributes"}
type java_security_cert_Certificate = {|
  encoded?: Binary, 
  publicKey?: java_security_PublicKey, 
  "type"?: String
|} {"typeAlias": "Certificate",
"typeId": "java.security.cert.Certificate"}
type java_security_PublicKey = {|  |} {"typeAlias": "PublicKey",
"typeId": "java.security.PublicKey"}





]]></types:shape>
    </types:type>
    <types:type name="auto_c6d7d691-eb14-4d53-bb75-54856400c996_Output-Payload" format="json">
      <types:shape format="weave" example="weave/autogenerated/c6d7d691-eb14-4d53-bb75-54856400c996/Output-Payload.wev" autogeneratedOrigin="ff7681b9-79f3-4584-87cd-5db80fe6230e"><![CDATA[%dw 2.0

type auto_c6d7d691_eb14_4d53_bb75_54856400c996_Output_Payload = {| message: Number |}

]]></types:shape>
    </types:type>
    <types:type name="auto_c6d7d691-eb14-4d53-bb75-54856400c996_Input-Payload" format="java">
      <types:shape format="weave" example="weave/autogenerated/c6d7d691-eb14-4d53-bb75-54856400c996/Input-Payload.wev" autogeneratedOrigin="ff7681b9-79f3-4584-87cd-5db80fe6230e"><![CDATA[%dw 2.0

type auto_c6d7d691_eb14_4d53_bb75_54856400c996_Input_Payload = Any

]]></types:shape>
    </types:type>
  </types:catalog>
  <types:enrichment select="#c6d7d691-eb14-4d53-bb75-54856400c996">
    <types:processor-declaration>
      <types:input-event>
        <types:message>
          <types:payload type="auto_c6d7d691-eb14-4d53-bb75-54856400c996_Input-Payload"/>
          <types:attributes type="auto_c6d7d691-eb14-4d53-bb75-54856400c996_Input-Attributes"/>
        </types:message>
      </types:input-event>
      <types:output-event>
        <types:message>
          <types:payload type="auto_c6d7d691-eb14-4d53-bb75-54856400c996_Output-Payload"/>
          <types:attributes type="auto_c6d7d691-eb14-4d53-bb75-54856400c996_Output-Attributes"/>
        </types:message>
      </types:output-event>
    </types:processor-declaration>
  </types:enrichment>
</types:mule>